AUTHORS
CHANGES
COPYING
INSTALL
MANIFEST.in
README
README.images
setup.py
bin/scanbooker-admin
bin/scanbooker-makeconfig
bin/scanbooker-test
src/scanbooker/__init__.py
src/scanbooker/accesscontrol.py
src/scanbooker/accesscontroltest.py
src/scanbooker/applicationtest.py
src/scanbooker/builder.py
src/scanbooker/commandtest.py
src/scanbooker/dictionary.py
src/scanbooker/dictionarywords.py
src/scanbooker/djangotest.py
src/scanbooker/domtest.py
src/scanbooker/exceptions.py
src/scanbooker/filesystem.py
src/scanbooker/ioc.py
src/scanbooker/migratetest.py
src/scanbooker/plugintest.py
src/scanbooker/regexps.py
src/scanbooker/soleInstance.py
src/scanbooker/testunit.py
src/scanbooker/unittesttest.py
src/scanbooker/url.py
src/scanbooker/workingHours.py
src/scanbooker.egg-info/PKG-INFO
src/scanbooker.egg-info/SOURCES.txt
src/scanbooker.egg-info/dependency_links.txt
src/scanbooker.egg-info/not-zip-safe
src/scanbooker.egg-info/requires.txt
src/scanbooker.egg-info/top_level.txt
src/scanbooker/application/__init__.py
src/scanbooker/cli/__init__.py
src/scanbooker/cli/admin.py
src/scanbooker/command/__init__.py
src/scanbooker/command/initialise.py
src/scanbooker/command/initialisetest.py
src/scanbooker/command/package.py
src/scanbooker/django/__init__.py
src/scanbooker/django/apps/__init__.py
src/scanbooker/django/apps/sui/__init__.py
src/scanbooker/django/apps/sui/test/__init__.py
src/scanbooker/django/apps/sui/test/package.py
src/scanbooker/django/apps/sui/test/admin/__init__.py
src/scanbooker/django/apps/sui/views/__init__.py
src/scanbooker/django/apps/sui/views/accesscontrol.py
src/scanbooker/django/apps/sui/views/base.py
src/scanbooker/django/apps/sui/views/image.py
src/scanbooker/django/apps/sui/views/manipulator.py
src/scanbooker/django/apps/sui/views/myspace.py
src/scanbooker/django/apps/sui/views/person.py
src/scanbooker/django/apps/sui/views/registry.py
src/scanbooker/django/apps/sui/views/registryExtn.py
src/scanbooker/django/apps/sui/views/rpc2.py
src/scanbooker/django/apps/sui/views/schedule.py
src/scanbooker/django/apps/sui/views/settings.py
src/scanbooker/django/apps/sui/views/testunit.py
src/scanbooker/django/apps/sui/views/volunteer.py
src/scanbooker/django/apps/sui/views/welcome.py
