Metadata-Version: 1.0
Name: scanbooker
Version: 0.23
Summary: The ScanBooker system is a domainmodel application which supports medical imaging administration.
Home-page: http://appropriatesoftware.net/scanbooker/Home.html
Author: Appropriate Software Foundation
Author-email: scanbooker-dev@appropriatesoftware.net
License: GPL
Platform: UNKNOWN
Classifier: Development Status :: 5 - Production/Stable
Classifier: Environment :: Console
Classifier: Environment :: Web Environment
Classifier: License :: OSI Approved :: GNU General Public License (GPL)
Classifier: Operating System :: OS Independent
Classifier: Programming Language :: Python
Classifier: Topic :: Software Development :: Libraries :: Python Modules
